yeeti/__init__.py
yeeti/zero_spinner/__init__.py
yeeti/zero_spinner/main.py
yeeti/zero_spinner/main_test.py
zero_spinner-0.1.1.dist-info/licenses/LICENSE
zero_spinner-0.1.1.dist-info/METADATA
zero_spinner-0.1.1.dist-info/WHEEL
zero_spinner-0.1.1.dist-info/top_level.txt
zero_spinner-0.1.1.dist-info/RECORD
