Metadata-Version: 2.4
Name: zero-spinner
Version: 0.1.1
Summary: A zero dependency spinner
Project-URL: Homepage, https://github.com/matteozambon89/python-zero-spinner
Project-URL: Changelog, https://github.com/matteozambon89/python-zero-spinner/releases
Project-URL: Issues, https://github.com/matteozambon89/python-zero-spinner/issues
Project-URL: CI, https://github.com/matteozambon89/python-zero-spinner/actions
Classifier: Programming Language :: Python
Classifier: Programming Language :: Python :: 3
Classifier: Programming Language :: Python :: 3.11
Classifier: Programming Language :: Python :: 3.12
Classifier: Programming Language :: Python :: 3.13
Classifier: Programming Language :: Python :: 3.14
Classifier: Development Status :: 4 - Beta
Classifier: Intended Audience :: Developers
Requires-Python: <4,>=3.11
License-File: LICENSE
Dynamic: license-file
